Workbook

Sheet Members
A1: Member_ID | B1: Name | C1: Phone_Email | D1: Active
A2: M001 | B2: Sample Member 1 | D2: Yes
A3: M002 | B3: Sample Member 2 | D3: Yes

Sheet Batches
A1: Batch_ID | B1: Start_Date | C1: Term_Months | D1: Share_Price | E1: Maturity_Date | F1: Status
A2: B001 | B2: 2026-03-01 | C2: 3 | D2: 2000 | E2: =EDATE(B2,C2) | F2: Open

Sheet Contributions
A1: Date | B1: Batch_ID | C1: Member_ID | D1: Shares | E1: Amount | F1: Source | G1: Source_Batch_ID
A2: 2026-03-01 | B2: B001 | C2: M001 | D2: 2 | E2: =D2*XLOOKUP(B2,Batches!A:A,Batches!D:D) | F2: Cash
A3: 2026-03-01 | B3: B001 | C3: M002 | D3: 1 | E3: =D3*XLOOKUP(B3,Batches!A:A,Batches!D:D) | F3: Cash
E4: =IF(OR(B4="",D4=""),"",D4*XLOOKUP(B4,Batches!A:A,Batches!D:D))
E5: =IF(OR(B5="",D5=""),"",D5*XLOOKUP(B5,Batches!A:A,Batches!D:D))
E6: =IF(OR(B6="",D6=""),"",D6*XLOOKUP(B6,Batches!A:A,Batches!D:D))
E7: =IF(OR(B7="",D7=""),"",D7*XLOOKUP(B7,Batches!A:A,Batches!D:D))
E8: =IF(OR(B8="",D8=""),"",D8*XLOOKUP(B8,Batches!A:A,Batches!D:D))
E9: =IF(OR(B9="",D9=""),"",D9*XLOOKUP(B9,Batches!A:A,Batches!D:D))
E10: =IF(OR(B10="",D10=""),"",D10*XLOOKUP(B10,Batches!A:A,Batches!D:D))
E11: =IF(OR(B11="",D11=""),"",D11*XLOOKUP(B11,Batches!A:A,Batches!D:D))
E12: =IF(OR(B12="",D12=""),"",D12*XLOOKUP(B12,Batches!A:A,Batches!D:D))
E13: =IF(OR(B13="",D13=""),"",D13*XLOOKUP(B13,Batches!A:A,Batches!D:D))
E14: =IF(OR(B14="",D14=""),"",D14*XLOOKUP(B14,Batches!A:A,Batches!D:D))
E15: =IF(OR(B15="",D15=""),"",D15*XLOOKUP(B15,Batches!A:A,Batches!D:D))
... E1000: =IF(OR(B1000="",D1000=""),"",D1000*XLOOKUP(B1000,Batches!A:A,Batches!D:D))

Sheet Returns
A1: Batch_ID | B1: Return_Date | C1: Total_Return | D1: Total_Principal | E1: Profit
A2: B001 | B2: 2026-06-01 | D2: =SUMIFS(Contributions!E:E,Contributions!B:B,A2) | E2: =IF(C2="","",C2-D2)
D3: =IF(A3="","",SUMIFS(Contributions!E:E,Contributions!B:B,A3)) | E3: =IF(OR(A3="",C3=""),"",C3-D3)
D4: =IF(A4="","",SUMIFS(Contributions!E:E,Contributions!B:B,A4)) | E4: =IF(OR(A4="",C4=""),"",C4-D4)
D5: =IF(A5="","",SUMIFS(Contributions!E:E,Contributions!B:B,A5)) | E5: =IF(OR(A5="",C5=""),"",C5-D5)
D6: =IF(A6="","",SUMIFS(Contributions!E:E,Contributions!B:B,A6)) | E6: =IF(OR(A6="",C6=""),"",C6-D6)
D7: =IF(A7="","",SUMIFS(Contributions!E:E,Contributions!B:B,A7)) | E7: =IF(OR(A7="",C7=""),"",C7-D7)
D8: =IF(A8="","",SUMIFS(Contributions!E:E,Contributions!B:B,A8)) | E8: =IF(OR(A8="",C8=""),"",C8-D8)
D9: =IF(A9="","",SUMIFS(Contributions!E:E,Contributions!B:B,A9)) | E9: =IF(OR(A9="",C9=""),"",C9-D9)
D10: =IF(A10="","",SUMIFS(Contributions!E:E,Contributions!B:B,A10)) | E10: =IF(OR(A10="",C10=""),"",C10-D10)
D11: =IF(A11="","",SUMIFS(Contributions!E:E,Contributions!B:B,A11)) | E11: =IF(OR(A11="",C11=""),"",C11-D11)
D12: =IF(A12="","",SUMIFS(Contributions!E:E,Contributions!B:B,A12)) | E12: =IF(OR(A12="",C12=""),"",C12-D12)
D13: =IF(A13="","",SUMIFS(Contributions!E:E,Contributions!B:B,A13)) | E13: =IF(OR(A13="",C13=""),"",C13-D13)
D14: =IF(A14="","",SUMIFS(Contributions!E:E,Contributions!B:B,A14)) | E14: =IF(OR(A14="",C14=""),"",C14-D14)
... D1000: =IF(A1000="","",SUMIFS(Contributions!E:E,Contributions!B:B,A1000)) | E1000: =IF(OR(A1000="",C1000=""),"",C1000-D1000)

Sheet Payouts
A1: Batch_ID | B1: Member_ID | C1: Principal | D1: Batch_Principal | E1: Batch_Profit | F1: Member_Profit | G1: Gross_Payout | H1: Reinvested | I1: Cashout
A2: =IFERROR(UNIQUE(FILTER(Contributions!B2:C10000,(Contributions!B2:B10000<>"")*(Contributions!C2:C10000<>""))),"") | C2: =IF($A2="","",SUMIFS(Contributions!E:E,Contributions!B:B,$A2,Contributions!C:C,$B2)) | D2: =IF($A2="","",SUMIFS(Contributions!E:E,Contributions!B:B,$A2)) | E2: =IF($A2="","",XLOOKUP($A2,Returns!A:A,Returns!E:E)) | F2: =IF(OR($A2="",D2=0),"",C2/D2*E2) | G2: =IF($A2="","",C2+F2) | H2: =IF($A2="","",SUMIFS(Contributions!E:E,Contributions!C:C,$B2,Contributions!F:F,"Reinvest",Contributions!G:G,$A2)) | I2: =IF($A2="","",G2-H2)
C3: =IF($A3="","",SUMIFS(Contributions!E:E,Contributions!B:B,$A3,Contributions!C:C,$B3)) | D3: =IF($A3="","",SUMIFS(Contributions!E:E,Contributions!B:B,$A3)) | E3: =IF($A3="","",XLOOKUP($A3,Returns!A:A,Returns!E:E)) | F3: =IF(OR($A3="",D3=0),"",C3/D3*E3) | G3: =IF($A3="","",C3+F3) | H3: =IF($A3="","",SUMIFS(Contributions!E:E,Contributions!C:C,$B3,Contributions!F:F,"Reinvest",Contributions!G:G,$A3)) | I3: =IF($A3="","",G3-H3)
C4: =IF($A4="","",SUMIFS(Contributions!E:E,Contributions!B:B,$A4,Contributions!C:C,$B4)) | D4: =IF($A4="","",SUMIFS(Contributions!E:E,Contributions!B:B,$A4)) | E4: =IF($A4="","",XLOOKUP($A4,Returns!A:A,Returns!E:E)) | F4: =IF(OR($A4="",D4=0),"",C4/D4*E4) | G4: =IF($A4="","",C4+F4) | H4: =IF($A4="","",SUMIFS(Contributions!E:E,Contributions!C:C,$B4,Contributions!F:F,"Reinvest",Contributions!G:G,$A4)) | I4: =IF($A4="","",G4-H4)
C5: =IF($A5="","",SUMIFS(Contributions!E:E,Contributions!B:B,$A5,Contributions!C:C,$B5)) | D5: =IF($A5="","",SUMIFS(Contributions!E:E,Contributions!B:B,$A5)) | E5: =IF($A5="","",XLOOKUP($A5,Returns!A:A,Returns!E:E)) | F5: =IF(OR($A5="",D5=0),"",C5/D5*E5) | G5: =IF($A5="","",C5+F5) | H5: =IF($A5="","",SUMIFS(Contributions!E:E,Contributions!C:C,$B5,Contributions!F:F,"Reinvest",Contributions!G:G,$A5)) | I5: =IF($A5="","",G5-H5)
C6: =IF($A6="","",SUMIFS(Contributions!E:E,Contributions!B:B,$A6,Contributions!C:C,$B6)) | D6: =IF($A6="","",SUMIFS(Contributions!E:E,Contributions!B:B,$A6)) | E6: =IF($A6="","",XLOOKUP($A6,Returns!A:A,Returns!E:E)) | F6: =IF(OR($A6="",D6=0),"",C6/D6*E6) | G6: =IF($A6="","",C6+F6) | H6: =IF($A6="","",SUMIFS(Contributions!E:E,Contributions!C:C,$B6,Contributions!F:F,"Reinvest",Contributions!G:G,$A6)) | I6: =IF($A6="","",G6-H6)
C7: =IF($A7="","",SUMIFS(Contributions!E:E,Contributions!B:B,$A7,Contributions!C:C,$B7)) | D7: =IF($A7="","",SUMIFS(Contributions!E:E,Contributions!B:B,$A7)) | E7: =IF($A7="","",XLOOKUP($A7,Returns!A:A,Returns!E:E)) | F7: =IF(OR($A7="",D7=0),"",C7/D7*E7) | G7: =IF($A7="","",C7+F7) | H7: =IF($A7="","",SUMIFS(Contributions!E:E,Contributions!C:C,$B7,Contributions!F:F,"Reinvest",Contributions!G:G,$A7)) | I7: =IF($A7="","",G7-H7)
C8: =IF($A8="","",SUMIFS(Contributions!E:E,Contributions!B:B,$A8,Contributions!C:C,$B8)) | D8: =IF($A8="","",SUMIFS(Contributions!E:E,Contributions!B:B,$A8)) | E8: =IF($A8="","",XLOOKUP($A8,Returns!A:A,Returns!E:E)) | F8: =IF(OR($A8="",D8=0),"",C8/D8*E8) | G8: =IF($A8="","",C8+F8) | H8: =IF($A8="","",SUMIFS(Contributions!E:E,Contributions!C:C,$B8,Contributions!F:F,"Reinvest",Contributions!G:G,$A8)) | I8: =IF($A8="","",G8-H8)
C9: =IF($A9="","",SUMIFS(Contributions!E:E,Contributions!B:B,$A9,Contributions!C:C,$B9)) | D9: =IF($A9="","",SUMIFS(Contributions!E:E,Contributions!B:B,$A9)) | E9: =IF($A9="","",XLOOKUP($A9,Returns!A:A,Returns!E:E)) | F9: =IF(OR($A9="",D9=0),"",C9/D9*E9) | G9: =IF($A9="","",C9+F9) | H9: =IF($A9="","",SUMIFS(Contributions!E:E,Contributions!C:C,$B9,Contributions!F:F,"Reinvest",Contributions!G:G,$A9)) | I9: =IF($A9="","",G9-H9)
C10: =IF($A10="","",SUMIFS(Contributions!E:E,Contributions!B:B,$A10,Contributions!C:C,$B10)) | D10: =IF($A10="","",SUMIFS(Contributions!E:E,Contributions!B:B,$A10)) | E10: =IF($A10="","",XLOOKUP($A10,Returns!A:A,Returns!E:E)) | F10: =IF(OR($A10="",D10=0),"",C10/D10*E10) | G10: =IF($A10="","",C10+F10) | H10: =IF($A10="","",SUMIFS(Contributions!E:E,Contributions!C:C,$B10,Contributions!F:F,"Reinvest",Contributions!G:G,$A10)) | I10: =IF($A10="","",G10-H10)
C11: =IF($A11="","",SUMIFS(Contributions!E:E,Contributions!B:B,$A11,Contributions!C:C,$B11)) | D11: =IF($A11="","",SUMIFS(Contributions!E:E,Contributions!B:B,$A11)) | E11: =IF($A11="","",XLOOKUP($A11,Returns!A:A,Returns!E:E)) | F11: =IF(OR($A11="",D11=0),"",C11/D11*E11) | G11: =IF($A11="","",C11+F11) | H11: =IF($A11="","",SUMIFS(Contributions!E:E,Contributions!C:C,$B11,Contributions!F:F,"Reinvest",Contributions!G:G,$A11)) | I11: =IF($A11="","",G11-H11)
C12: =IF($A12="","",SUMIFS(Contributions!E:E,Contributions!B:B,$A12,Contributions!C:C,$B12)) | D12: =IF($A12="","",SUMIFS(Contributions!E:E,Contributions!B:B,$A12)) | E12: =IF($A12="","",XLOOKUP($A12,Returns!A:A,Returns!E:E)) | F12: =IF(OR($A12="",D12=0),"",C12/D12*E12) | G12: =IF($A12="","",C12+F12) | H12: =IF($A12="","",SUMIFS(Contributions!E:E,Contributions!C:C,$B12,Contributions!F:F,"Reinvest",Contributions!G:G,$A12)) | I12: =IF($A12="","",G12-H12)
C13: =IF($A13="","",SUMIFS(Contributions!E:E,Contributions!B:B,$A13,Contributions!C:C,$B13)) | D13: =IF($A13="","",SUMIFS(Contributions!E:E,Contributions!B:B,$A13)) | E13: =IF($A13="","",XLOOKUP($A13,Returns!A:A,Returns!E:E)) | F13: =IF(OR($A13="",D13=0),"",C13/D13*E13) | G13: =IF($A13="","",C13+F13) | H13: =IF($A13="","",SUMIFS(Contributions!E:E,Contributions!C:C,$B13,Contributions!F:F,"Reinvest",Contributions!G:G,$A13)) | I13: =IF($A13="","",G13-H13)
C14: =IF($A14="","",SUMIFS(Contributions!E:E,Contributions!B:B,$A14,Contributions!C:C,$B14)) | D14: =IF($A14="","",SUMIFS(Contributions!E:E,Contributions!B:B,$A14)) | E14: =IF($A14="","",XLOOKUP($A14,Returns!A:A,Returns!E:E)) | F14: =IF(OR($A14="",D14=0),"",C14/D14*E14) | G14: =IF($A14="","",C14+F14) | H14: =IF($A14="","",SUMIFS(Contributions!E:E,Contributions!C:C,$B14,Contributions!F:F,"Reinvest",Contributions!G:G,$A14)) | I14: =IF($A14="","",G14-H14)
... C1000: =IF($A1000="","",SUMIFS(Contributions!E:E,Contributions!B:B,$A1000,Contributions!C:C,$B1000)) | D1000: =IF($A1000="","",SUMIFS(Contributions!E:E,Contributions!B:B,$A1000)) | E1000: =IF($A1000="","",XLOOKUP($A1000,Returns!A:A,Returns!E:E)) | F1000: =IF(OR($A1000="",D1000=0),"",C1000/D1000*E1000) | G1000: =IF($A1000="","",C1000+F1000) | H1000: =IF($A1000="","",SUMIFS(Contributions!E:E,Contributions!C:C,$B1000,Contributions!F:F,"Reinvest",Contributions!G:G,$A1000)) | I1000: =IF($A1000="","",G1000-H1000)

Sheet Dashboard
A1: Metric | B1: Value
A2: Today | B2: =TODAY()
A3: Open Batches | B3: =COUNTIF(Batches!F:F,"Open")
A4: Total Principal Invested | B4: =SUM(Contributions!E:E)
A5: Total Profit Realized | B5: =SUM(Returns!E:E)
A6: Total Cashout | B6: =SUM(Payouts!I:I)
A7: Total Reinvested | B7: =SUM(Payouts!H:H)
A8: Upcoming Maturities (30 Days) | B8: =COUNTIFS(Batches!E:E,">="&TODAY(),Batches!E:E,"<="&TODAY()+30)

Sheet Instructions
A1: How to use this template (v2):
A2: 1) Add all people in Members with unique Member_ID values.
A3: 2) Add each investment round in Batches. Maturity_Date is auto-calculated.
A4: 3) Add Contributions rows. Use Source dropdown: Cash or Reinvest.
A5: 4) Amount is auto-calculated from Shares and Batch Share_Price.
A6: 5) When a batch matures, enter Total_Return in Returns.
A7: 6) Payouts sheet auto-generates Batch_ID + Member_ID pairs from Contributions.
A8: 7) If a member reinvests from an old batch, create a new Contributions row with Source=Reinvest and Source_Batch_ID = old batch.
A9: 8) Cashout = Gross_Payout - Reinvested.
